pdfa3extractor/__init__.py
pdfa3extractor/extractor.py
pdfa3extractor-2.0.dist-info/METADATA
pdfa3extractor-2.0.dist-info/WHEEL
pdfa3extractor-2.0.dist-info/entry_points.txt
pdfa3extractor-2.0.dist-info/top_level.txt
pdfa3extractor-2.0.dist-info/RECORD
