Metadata-Version: 2.1
Name: pdfa3extractor
Version: 2.0
Summary: A tool to extract embedded XML files from PDF/A-3 documents
Home-page: https://github.com/PierreGode/pdfa3extractor
Author: PierreGode
Author-email: pierre@gode.one
Classifier: Programming Language :: Python :: 3
Classifier: License :: OSI Approved :: MIT License
Classifier: Operating System :: OS Independent
Requires-Python: >=3.6
Requires-Dist: pymupdf
